todotxt-0.0.2.dist-info/DESCRIPTION.rst
todotxt-0.0.2.dist-info/WHEEL
todotxt-0.0.2.dist-info/METADATA
todotxt-0.0.2.dist-info/RECORD
todotxt-0.0.2.dist-info/metadata.json
todotxt-0.0.2.dist-info/top_level.txt
todotxt/__init__.py
