Metadata-Version: 2.0
Name: todotxt
Version: 0.0.2
Summary: A Python library for dealing with todo.txt files
Home-page: https://github.com/mrshu/py-todotxt
Author: mrshu
Author-email: mr@shu.io
License: UNKNOWN
Keywords: todotxt
Platform: UNKNOWN
Classifier: Development Status :: 3 - Alpha
Classifier: Intended Audience :: Developers
Classifier: Topic :: Software Development :: Libraries
Classifier: Topic :: Software Development :: Libraries :: Python Modules
Classifier: Programming Language :: Python :: 2
Classifier: Programming Language :: Python :: 2.6
Classifier: Programming Language :: Python :: 2.7
Classifier: Programming Language :: Python :: 3
Classifier: Programming Language :: Python :: 3.2
Classifier: Programming Language :: Python :: 3.3
Classifier: Programming Language :: Python :: 3.4
